Tensorlib/Tensorlib.py
Tensorlib/__init__.py
npTensor/__init__.py
npTensor/Tensorlib/Tensorlib.py
npTensor/Tensorlib/__init__.py
nptensor-0.1.4.dist-info/licenses/LICENSE
nptensor-0.1.4.dist-info/METADATA
nptensor-0.1.4.dist-info/WHEEL
nptensor-0.1.4.dist-info/top_level.txt
nptensor-0.1.4.dist-info/RECORD
